fluent_pages/__init__.py
fluent_pages/apps.py
fluent_pages/appsettings.py
fluent_pages/sitemaps.py
fluent_pages/tests_all.py
fluent_pages/urlresolvers.py
fluent_pages/urls.py
fluent_pages/admin/__init__.py
fluent_pages/admin/utils.py
fluent_pages/adminui/__init__.py
fluent_pages/adminui/htmlpageadmin.py
fluent_pages/adminui/overrides.py
fluent_pages/adminui/pageadmin.py
fluent_pages/adminui/pagelayoutadmin.py
fluent_pages/adminui/urlnodechildadmin.py
fluent_pages/adminui/urlnodeparentadmin.py
fluent_pages/adminui/utils.py
fluent_pages/extensions/__init__.py
fluent_pages/extensions/pagetypebase.py
fluent_pages/extensions/pagetypepool.py
fluent_pages/forms/__init__.py
fluent_pages/forms/fields.py
fluent_pages/integration/__init__.py
fluent_pages/integration/fluent_contents/__init__.py
fluent_pages/integration/fluent_contents/admin.py
fluent_pages/integration/fluent_contents/models.py
fluent_pages/integration/fluent_contents/page_type_plugins.py
fluent_pages/locale/en/LC_MESSAGES/django.mo
fluent_pages/locale/en/LC_MESSAGES/django.po
fluent_pages/locale/es/LC_MESSAGES/django.mo
fluent_pages/locale/es/LC_MESSAGES/django.po
fluent_pages/locale/nl/LC_MESSAGES/django.mo
fluent_pages/locale/nl/LC_MESSAGES/django.po
fluent_pages/management/__init__.py
fluent_pages/management/commands/__init__.py
fluent_pages/management/commands/make_language_redirects.py
fluent_pages/management/commands/prefix_pagetypes.py
fluent_pages/management/commands/rebuild_page_tree.py
fluent_pages/migrations/0001_initial.py
fluent_pages/migrations/__init__.py
fluent_pages/models/__init__.py
fluent_pages/models/db.py
fluent_pages/models/fields.py
fluent_pages/models/managers.py
fluent_pages/models/navigation.py
fluent_pages/models/utils.py
fluent_pages/pagetypes/__init__.py
fluent_pages/pagetypes/flatpage/__init__.py
fluent_pages/pagetypes/flatpage/admin.py
fluent_pages/pagetypes/flatpage/appsettings.py
fluent_pages/pagetypes/flatpage/models.py
sigmacms_fluent_pages-1.0.1.dist-info/DESCRIPTION.rst
sigmacms_fluent_pages-1.0.1.dist-info/METADATA
sigmacms_fluent_pages-1.0.1.dist-info/metadata.json
sigmacms_fluent_pages-1.0.1.dist-info/RECORD
sigmacms_fluent_pages-1.0.1.dist-info/top_level.txt
sigmacms_fluent_pages-1.0.1.dist-info/WHEEL
