Metadata-Version: 2.0
Name: sigmacms-fluent-pages
Version: 1.0.1
Summary: A flexible, scalable CMS with custom node types, and flexible block content.
Home-page: https://github.com/sigmacms/sigmacms-fluent-pages
Author: Diederik van der Boor
Author-email: opensource@edoburu.nl
License: Apache 2.0
Download-URL: https://github.com/sigmacms/sigmacms-fluent-pages/zipball/master
Platform: UNKNOWN
Classifier: Development Status :: 4 - Beta
Classifier: Environment :: Web Environment
Classifier: Intended Audience :: Developers
Classifier: License :: OSI Approved :: Apache Software License
Classifier: Operating System :: OS Independent
Classifier: Programming Language :: Python
Classifier: Programming Language :: Python :: 2.6
Classifier: Programming Language :: Python :: 2.7
Classifier: Programming Language :: Python :: 3.3
Classifier: Framework :: Django
Classifier: Framework :: Django :: 1.6
Classifier: Framework :: Django :: 1.7
Classifier: Framework :: Django :: 1.8
Classifier: Topic :: Internet :: WWW/HTTP
Classifier: Topic :: Internet :: WWW/HTTP :: Dynamic Content
Classifier: Topic :: Software Development :: Libraries :: Application Frameworks
Classifier: Topic :: Software Development :: Libraries :: Python Modules
Requires: Django (>=1.5)
Requires-Dist: django-fluent-utils (>=1.2.3)
Requires-Dist: django-mptt (>=0.5.5,!=0.8.5)
Requires-Dist: django-parler (>=1.6.1)
Requires-Dist: django-polymorphic (>=0.9.1)
Requires-Dist: sigmacms-polymorphic-tree (>=1.2.3)
Requires-Dist: django-slug-preview (>=1.0.1)
Requires-Dist: django-tag-parser (>=2.1)
Requires-Dist: future (>=0.12.2)
Requires-Dist: six (>=1.5.2)
Provides-Extra: flatpage
Requires-Dist: django-wysiwyg (>=0.7.1); extra == 'flatpage'
Provides-Extra: fluentpage
Requires-Dist: django-fluent-contents (>=1.1); extra == 'fluentpage'
Provides-Extra: redirectnode
Requires-Dist: django-any-urlfield (>=2.2); extra == 'redirectnode'
